menglingflow_tools/__init__.py
menglingflow_tools/mg_task_dispatch.py
menglingflow_tools/node_process.py
menglingflow_tools/thread_work.py
menglingflow_tools-1.2.10.dist-info/METADATA
menglingflow_tools-1.2.10.dist-info/WHEEL
menglingflow_tools-1.2.10.dist-info/top_level.txt
menglingflow_tools-1.2.10.dist-info/RECORD
