Metadata-Version: 2.1
Name: menglingflow-tools
Version: 1.2.10
Summary: 工业化! yyds
Home-page: https://www.python.org
Author: mengling
Author-email: 1321443305@qq.com
Requires-Python: >3.6
